{
  "agent": "weer-agent",
  "type": "weer",
  "datum": "2026-07-05",
  "bron": "cyclingstage / accuweather (weersverwachting Tarragona-Barcelona 5 juli 2026)",
  "weer": "Etappe 2 (zo 5/7, Tarragona → Barcelona, 168,5 km langs de Middellandse Zeekust): warm en zonnig. Start ~34°C met zuidenwind (~21 km/h), aankomst in Barcelona ~30°C met zuidenwind (~16 km/h). Nagenoeg geen regenkans.",
  "impact": "Zonnige, warme rit met een zuidelijke mee-/zijwind die zorgt voor een snelle aanloop naar de finaleronde. De rit wordt beslist op 3 passages van de steile Côte de Montjuïc (9,3%, tot 13%): een puncheursfinale waar de hitte en de herhaalde korte inspanningen de klimmende puncheurs en klassementsrenners bevoordelen. Sprinters kunnen hier niet volgen."
}
